android_asset_resizer/__init__.py
android_asset_resizer/resizer.py
android_asset_resizer-1.3.1.data/scripts/aaresize
android_asset_resizer-1.3.1.dist-info/DESCRIPTION.rst
android_asset_resizer-1.3.1.dist-info/METADATA
android_asset_resizer-1.3.1.dist-info/RECORD
android_asset_resizer-1.3.1.dist-info/WHEEL
android_asset_resizer-1.3.1.dist-info/metadata.json
android_asset_resizer-1.3.1.dist-info/top_level.txt
