Metadata-Version: 2.0
Name: android-asset-resizer
Version: 1.3.1
Summary: A command-line utility for generating Android drawables in the required densities.
Home-page: https://github.com/twaddington/android-asset-resizer
Author: Tristan Waddington
Author-email: tristan.waddington@gmail.com
License: UNKNOWN
Keywords: android asset resource res drawable resizer
Platform: UNKNOWN
Classifier: Development Status :: 5 - Production/Stable
Classifier: Environment :: Console
Classifier: Environment :: Web Environment
Classifier: Intended Audience :: Developers
Classifier: License :: OSI Approved :: Apache Software License
Classifier: Operating System :: OS Independent
Classifier: Programming Language :: Python
Requires-Dist: pillow
